app_tools_zxw/__init__.py
app_tools_zxw/configs.py
app_tools_zxw/models_payment.py
app_tools_zxw/支付服务_代码规范.py
app_tools_zxw/Errors/__init__.py
app_tools_zxw/Errors/api_errors.py
app_tools_zxw/Funcs/__init__.py
app_tools_zxw/Funcs/async_logger.py
app_tools_zxw/Funcs/fastapi_logger.py
app_tools_zxw/Funcs/生成订单号.py
app_tools_zxw/SDK_jwt/__init__.py
app_tools_zxw/SDK_jwt/demo.py
app_tools_zxw/SDK_jwt/jwt.py
app_tools_zxw/SDK_jwt/jwt_刷新管理.py
app_tools_zxw/SDK_jwt/apis/__init__.py
app_tools_zxw/SDK_jwt/apis/api_刷新token.py
app_tools_zxw/SDK_jwt/db_model/__init__.py
app_tools_zxw/SDK_jwt/db_model/model.py
app_tools_zxw/SDK_云存储_async/__init__.py
app_tools_zxw/SDK_云存储_async/async阿里云OSS.py
app_tools_zxw/SDK_微信/__init__.py
app_tools_zxw/SDK_微信/SDK_微信公众号或网站应用/__init__.py
app_tools_zxw/SDK_微信/SDK_微信公众号或网站应用/获取_openid和access_token.py
app_tools_zxw/SDK_微信/SDK_微信公众号或网站应用/获取_登录二维码URL.py
app_tools_zxw/SDK_微信/SDK_微信公众号或网站应用/apis/__init__.py
app_tools_zxw/SDK_微信/SDK_微信公众号或网站应用/apis/api_用户信息.py
app_tools_zxw/SDK_微信/SDK_微信公众号或网站应用/apis/api_登录二维码.py
app_tools_zxw/SDK_微信/SDK_微信小程序/__init__.py
app_tools_zxw/SDK_微信/SDK_微信小程序/step1_维护小程序准入码.py
app_tools_zxw/SDK_微信/SDK_微信小程序/获取_openid和sessionKey.py
app_tools_zxw/SDK_微信/SDK_微信小程序/获取小程序二维码.py
app_tools_zxw/SDK_微信/SDK_微信小程序/解密_用户信息.py
app_tools_zxw/SDK_微信/SDK_微信小程序/apis/__init__.py
app_tools_zxw/SDK_微信/SDK_微信小程序/apis/api_用户信息.py
app_tools_zxw/SDK_微信/SDK_微信小程序/发送订阅消息/__init__.py
app_tools_zxw/SDK_微信/SDK_微信小程序/发送订阅消息/发送订阅消息.py
app_tools_zxw/SDK_微信/SDK_微信小程序/发送订阅消息/模板_发货提醒.py
app_tools_zxw/SDK_微信/SDK_微信支付/__init__.py
app_tools_zxw/SDK_微信/SDK_微信支付/支付服务_小程序.py
app_tools_zxw/SDK_微信/SDK_微信支付/返回值模型.py
app_tools_zxw/SDK_微信/SDK_微信支付/minipay/__init__.py
app_tools_zxw/SDK_微信/SDK_微信支付/minipay/base.py
app_tools_zxw/SDK_微信/SDK_微信支付/minipay/config.py
app_tools_zxw/SDK_微信/SDK_微信支付/minipay/exceptions.py
app_tools_zxw/SDK_微信/SDK_微信支付/minipay/model.py
app_tools_zxw/SDK_微信/SDK_微信支付v2/__init__.py
app_tools_zxw/SDK_微信/SDK_微信支付v2/支付服务_二维码.py
app_tools_zxw-2.2.4.dist-info/METADATA
app_tools_zxw-2.2.4.dist-info/WHEEL
app_tools_zxw-2.2.4.dist-info/top_level.txt
app_tools_zxw-2.2.4.dist-info/RECORD
