Metadata-Version: 2.4
Name: app_tools_zxw
Version: 2.2.4
Summary: app开发相关的各种sdk
Home-page: https://github.com/sunshineinwater/
Author: 薛伟的小工具
Author-email: 
Classifier: Programming Language :: Python :: 3.10
Classifier: License :: OSI Approved :: MIT License
Classifier: Operating System :: OS Independent
Requires-Dist: pycryptodome<=3.22.0,>=3.20.0
Requires-Dist: fastapi<0.113,>=0.112.0
Requires-Dist: jose<1.1.0,>=1.0.0
Requires-Dist: aiohttp>=3.12.14
Requires-Dist: httpx>=0.28.1
Requires-Dist: qrcode<7.5.0,>=7.4.2
Requires-Dist: cryptography==44.0.1
Requires-Dist: alipay-zxw==0.0.4
Requires-Dist: aiofiles==24.1.0
Requires-Dist: app-store-server-library[async]==1.9.0
Dynamic: author
Dynamic: classifier
Dynamic: description
Dynamic: description-content-type
Dynamic: home-page
Dynamic: requires-dist
Dynamic: summary
